pyvigate/__init__.py
pyvigate/ai/__init__.py
pyvigate/ai/prompt_engineering.py
pyvigate/ai/query_engine.py
pyvigate/config/__init__.py
pyvigate/core/__init__.py
pyvigate/core/engine.py
pyvigate/core/login.py
pyvigate/modules/__init__.py
pyvigate/services/__init__.py
pyvigate/services/caching/__init__.py
pyvigate/services/caching/caching.py
pyvigate/services/scraping/__init__.py
pyvigate/services/scraping/prompts.py
pyvigate/services/scraping/scraping.py
pyvigate-0.0.3.dist-info/LICENSE
pyvigate-0.0.3.dist-info/METADATA
pyvigate-0.0.3.dist-info/WHEEL
pyvigate-0.0.3.dist-info/top_level.txt
pyvigate-0.0.3.dist-info/RECORD
