Metadata-Version: 2.1
Name: pyvigate
Version: 0.0.3
Summary: A brief description of what your package does
Home-page: https://github.com/kindsmiles/pyvigate
Author: Abhijith Neil Abraham
Author-email: abhijithneilabrahampk@gmail.com
Classifier: Programming Language :: Python :: 3
Classifier: License :: OSI Approved :: MIT License
Classifier: Operating System :: OS Independent
Requires-Python: >=3.8
License-File: LICENSE
Requires-Dist: pytest-playwright
Requires-Dist: beautifulsoup4
Requires-Dist: python-dotenv
Requires-Dist: llama-index
Requires-Dist: mkdocs
Requires-Dist: mkdocstrings
Provides-Extra: docs
Requires-Dist: sphinx (>=3.0) ; extra == 'docs'
Requires-Dist: sphinx-rtd-theme ; extra == 'docs'
